[
    {
        "name": "preslav",
        "displayname": "Жилищна кооперация",
        "description": "",
        "frontimage": "dsc_0018.jpg",
        "client": "Иван Караилански",
        "carousel": ["dsc_0018.jpg"],
        "place": "ул. Преслав, Пловдив",
        "endyear": "2016",
        "jilishtno": true,
        "promishleno": false,
        "infrastruktura": false,
        "obshtestveni": false
    },
    {
        "name": "starosel",
        "displayname": "Старосел",
        "description": "22222222222222222222222",
        "frontimage": "dsc_0161.jpg",
        "client": "БалканТабако",
        "carousel": ["dsc_0145.jpg", "dsc_0153.jpg", "dsc_0161.jpg", "dsc_0167.jpg", "dsc_0174.jpg", "dsc_0176.jpg"],
        "place": "с. Старосел",
        "endyear": "2016",
        "jilishtno": false,
        "promishleno": true,
        "infrastruktura": false,
        "obshtestveni": false
    },
    {
        "name": "leksi",
        "displayname": "Лекси",
        "description": "22222222222222222222222",
        "frontimage": "dsc_1407.jpg",
        "client": "Алекс Трейд 2010 ЕООД",
        "carousel": ["dsc_1407.jpg", "dsc_1410.jpg", "dsc_1411.jpg"],
        "place": "бул. Марица 19, Пловдив",
        "endyear": "2016",
        "jilishtno": false,
        "promishleno": true,
        "infrastruktura": false,
        "obshtestveni": false
    },
    {
        "name": "praktiker",
        "displayname": "Практикер",
        "description": "22222222222222222222222",
        "frontimage": "dsc_1430.jpg",
        "client": "Микс Констръкшън ООД",
        "carousel": ["dsc_1424.jpg", "dsc_1430.jpg"],
        "place": "бул. Кукленско шосе 9, Пловдив",
        "endyear": "2016",
        "jilishtno": false,
        "promishleno": true,
        "infrastruktura": false,
        "obshtestveni": false
    },
    {
        "name": "colori",
        "displayname": "Колори",
        "description": "1111111111111111111111",
        "frontimage": "dsc_0010.jpg",
        "client": "Колори 2005 ЕООД",
        "carousel": ["dsc_0010.jpg", "dsc_0015.jpg"],
        "place": "ул. Георги Бенев 5, Пловдив",
        "endyear": "2016",
        "jilishtno": false,
        "promishleno": true,
        "infrastruktura": false,
        "obshtestveni": false
    },
    {
        "name": "novotela",
        "displayname": "До новотела",
        "description": "22222222222222222222222",
        "frontimage": "dsc_1415.jpg",
        "client": "С.И.Т. ООД",
        "carousel": ["dsc_1415.jpg"],
        "place": "ул. Средец 46, Пловдив",
        "endyear": "2016",
        "jilishtno": true,
        "promishleno": false,
        "infrastruktura": false,
        "obshtestveni": false
    },
    {
        "name": "suedinenie",
        "displayname": "До съединение",
        "description": "22222222222222222222222",
        "frontimage": "dsc_1468.jpg",
        "client": "???????",
        "carousel": ["dsc_1468.jpg", "dsc_1471.jpg"],
        "place": "ул. Димитър Цончев 3, Пловдив",
        "endyear": "2016",
        "jilishtno": true,
        "promishleno": false,
        "infrastruktura": false,
        "obshtestveni": false
    },
    {
        "name": "hankardam",
        "displayname": "Хан Кардам",
        "description": "22222222222222222222222",
        "frontimage": "dsc_1439.jpg",
        "client": "С.И.Т. ООД",
        "carousel": ["dsc_1438.jpg", "dsc_1439.jpg"],
        "place": "ул. Хан Кардам 8, Пловдив",
        "endyear": "2016",
        "jilishtno": true,
        "promishleno": false,
        "infrastruktura": false,
        "obshtestveni": false
    },
    {
        "name": "hristobotev",
        "displayname": "ОУ Христо Ботев Съединение",
        "description": "22222222222222222222222",
        "frontimage": "dsc_0140.jpg",
        "client": "Община Съединение",
        "carousel": ["dsc_0128.jpg", "dsc_0134.jpg", "dsc_0136.jpg", "dsc_0140.jpg"],
        "place": "ул. Отец Паисий 14, Съединение",
        "endyear": "2016",
        "jilishtno": false,
        "promishleno": false,
        "infrastruktura": true,
        "obshtestveni": true
    },
    {
        "name": "curkva",
        "displayname": "Църква",
        "description": "22222222222222222222222",
        "frontimage": "dsc_0183.jpg",
        "client": "ЕВАНГЕЛСКА ПЕТДЕСЯТНА ЦЪРКВА СВЕТА ТРОИЦА – ГР. ПЛОВДИВ",
        "carousel": ["dsc_0183.jpg", "dsc_0182.jpg"],
        "place": "местоположение",
        "endyear": "2016",
        "jilishtno": false,
        "promishleno": false,
        "infrastruktura": false,
        "obshtestveni": false
    },
    {
        "name": "nissan",
        "displayname": "Нисан",
        "description": "22222222222222222222222",
        "frontimage": "dsc_1464.jpg",
        "client": "клиент проект 2",
        "carousel": ["dsc_1460.jpg", "dsc_1463.jpg", "dsc_1464.jpg", "dsc_1465.jpg"],
        "place": "местоположение",
        "endyear": "2016",
        "jilishtno": false,
        "promishleno": true,
        "infrastruktura": false,
        "obshtestveni": false
    },
    {
        "name": "peristera",
        "displayname": "Перистера",
        "description": "22222222222222222222222",
        "frontimage": "dsc_0195.jpg",
        "client": "Община Пещера",
        "carousel": ["dsc_0195.jpg", "dsc_0202.jpg", "dsc_0205.jpg", "dsc_0209.jpg", "dsc_0212.jpg", "dsc_0226.jpg", "dsc_0239.jpg"],
        "place": "хълм Света Петка, Пещера",
        "endyear": "2016",
        "jilishtno": false,
        "promishleno": false,
        "infrastruktura": false,
        "obshtestveni": true
    },
    {
        "name": "put_peshtera",
        "displayname": "Път Пещера",
        "description": "22222222222222222222222",
        "frontimage": "dsc_0256.jpg",
        "client": "Община Пещера",
        "carousel": ["dsc_0256.jpg", "dsc_0259.jpg", "dsc_0262.jpg"],
        "place": "ул. Хан Пресиян, Пещера",
        "endyear": "2016",
        "jilishtno": false,
        "promishleno": false,
        "infrastruktura": true,
        "obshtestveni": true
    },
    {
        "name": "peshtera",
        "displayname": "Пещера",
        "description": "22222222222222222222222",
        "frontimage": "dsc_0244.jpg",
        "client": "клиент проект 2",
        "carousel": ["dsc_0242.jpg", "dsc_0244.jpg", "dsc_0245.jpg", "dsc_0249.jpg", "dsc_0251.jpg"],
        "place": "местоположение",
        "endyear": "2016",
        "jilishtno": false,
        "promishleno": true,
        "infrastruktura": false,
        "obshtestveni": false
    }
]